CHANGES
LICENSE
README.md
setup.py
bin/pdns-create-zone
powerdns/__init__.py
powerdns/client.py
powerdns/exceptions.py
powerdns/interface.py
python_powerdns.egg-info/PKG-INFO
python_powerdns.egg-info/SOURCES.txt
python_powerdns.egg-info/dependency_links.txt
python_powerdns.egg-info/top_level.txt