Metadata-Version: 2.1
Name: python-powerdns
Version: 0.2.1
Summary: PowerDNS web api python client and interface
Home-page: https://github.com/vente-privee/python-powerdns
Author: Denis Pompilio (jawa)
Author-email: dpompilio@vente-privee.com
Maintainer: Denis Pompilio (jawa)
Maintainer-email: dpompilio@vente-privee.com
License: MIT
Keywords: dns,powerdns,api
Platform: UNIX
Classifier: Development Status :: 5 - Production/Stable
Classifier: Operating System :: POSIX :: BSD
Classifier: Operating System :: POSIX :: Linux
Classifier: License :: OSI Approved :: MIT License
Classifier: Programming Language :: Python :: 2.7
Classifier: Programming Language :: Python :: 3.4
Classifier: Programming Language :: Python :: 3.5
Classifier: Programming Language :: Python :: 3.6
Classifier: Environment :: Web Environment
Classifier: Topic :: Utilities
Requires: urllib3
Requires: requests
